Metadata-Version: 2.1
Name: django-configurations-wsgi
Version: 2020.7.3
Summary: django-configurations wsgi
Home-page: https://github.com/andrewp-as-is/django-configurations-wsgi.py
License: Unlicense
Keywords: django-configurations wsgi
Platform: UNKNOWN
Classifier: Framework :: Django
Classifier: License :: Public Domain
Classifier: Operating System :: OS Independent
